GaussianAnsatz/__init__.py
GaussianAnsatz/_version.py
GaussianAnsatz/archs.py
GaussianAnsatz/dnn.py
GaussianAnsatz/factorizer.py
GaussianAnsatz/utils.py
gaussianansatz-0.0.1.dist-info/METADATA
gaussianansatz-0.0.1.dist-info/WHEEL
gaussianansatz-0.0.1.dist-info/RECORD
