Metadata-Version: 2.1
Name: gaussianansatz
Version: 0.0.1
Summary: Tensorflow package for building neural networks capable of frequentist inference and uncertainty estimation
Project-URL: Documentation, https://github.com/rikab/GaussianAnsatz
Project-URL: Homepage, https://github.com/rikab/GaussianAnsatz
Project-URL: Issue Tracker, https://github.com/rikab/GaussianAnsatz/issues
Project-URL: Releases, https://github.com/rikab/GaussianAnsatz/releases
Project-URL: Source Code, https://github.com/rikab/GaussianAnsatz
Author-email: Rikab Gambhir <rikab@mit.edu>
License: MIT
Keywords: frequentist inference,jet physics,uncertainty estimation
Classifier: Development Status :: 3 - Alpha
Classifier: Intended Audience :: Science/Research
Classifier: License :: OSI Approved :: MIT License
Classifier: Programming Language :: Python :: 3
Classifier: Programming Language :: Python :: 3 :: Only
Classifier: Programming Language :: Python :: 3.7
Classifier: Programming Language :: Python :: 3.8
Classifier: Programming Language :: Python :: 3.9
Classifier: Programming Language :: Python :: 3.10
Classifier: Programming Language :: Python :: Implementation :: CPython
Classifier: Topic :: Scientific/Engineering
Classifier: Topic :: Scientific/Engineering :: Physics
Requires-Python: >=3.7
Requires-Dist: energyflow>=1.3.0
Requires-Dist: matplotlib>=3.5.0
Requires-Dist: numpy
Requires-Dist: scipy>=1.5.1
Requires-Dist: tensorflow-macos>=2.1.0; platform_machine == 'arm64' and platform_system == 'Darwin'
Requires-Dist: tensorflow>=2.1.0; platform_machine != 'arm64'
